neuralcat/__init__.py
neuralcat/datasets.py
neuralcat/layers.py
neuralcat/loss.py
neuralcat/losses.py
neuralcat/nn.py
neuralcat/optim.py
neuralcat/optimize.py
neuralcat/tensor.py
neuralcat_RedCatTeam-1.0.3.dist-info/LICENSE
neuralcat_RedCatTeam-1.0.3.dist-info/METADATA
neuralcat_RedCatTeam-1.0.3.dist-info/WHEEL
neuralcat_RedCatTeam-1.0.3.dist-info/top_level.txt
neuralcat_RedCatTeam-1.0.3.dist-info/RECORD
